argparse_schemas/__init__.py
argparse_schemas/jsonschema.py
argparse_schemas-0.2.0.dist-info/licenses/LICENSE
argparse_schemas-0.2.0.dist-info/METADATA
argparse_schemas-0.2.0.dist-info/WHEEL
argparse_schemas-0.2.0.dist-info/top_level.txt
argparse_schemas-0.2.0.dist-info/RECORD
