Metadata-Version: 2.4
Name: argparse-schemas
Version: 0.2.0
Summary: Transform argparse specs to JSON schemas
License-Expression: Apache-2.0
Project-URL: Homepage, https://github.com/lisa-sgs/argparse-schemas
Project-URL: Source, https://github.com/lisa-sgs/argparse-schemas
Project-URL: Issues, https://github.com/lisa-sgs/argparse-schemas/issues
Project-URL: Changelog, https://github.com/lisa-sgs/argparse-schemas/blob/develop/CHANGELOG.md
Requires-Python: >=3.11
License-File: LICENSE
Dynamic: license-file
